sry.py
sry-0.0.4.dist-info/METADATA
sry-0.0.4.dist-info/WHEEL
sry-0.0.4.dist-info/top_level.txt
sry-0.0.4.dist-info/RECORD
