Metadata-Version: 2.1
Name: sry
Version: 0.0.4
Summary: sry模块
